Metadata-Version: 2.4
Name: wizardextract
Version: 1.0.1
Summary: Text extraction from PDFs, Word files, spreadsheets, and images. Local OCR with Tesseract and optional Azure Document Intelligence for text, tables, and key–value pairs. Includes page/sheet selection and a hybrid PDF mode.
Author-email: Mattia Rubino <textwizard.dev@gmail.com>
License: WizardExtract — Copyright (C) 2024–2025 Mattia Rubino
Project-URL: Homepage, https://github.com/textwizard-dev/wizardextract
Project-URL: Source, https://github.com/textwizard-dev/wizardextract
Project-URL: Documentation, https://wizardextract.readthedocs.io/en/latest/
Keywords: text-extraction,ocr,tesseract,pdf,docx,xls,xlsx,azure-document-intelligence,tables,key-value
Classifier: Programming Language :: Python :: 3
Classifier: Programming Language :: Python :: 3.9
Classifier: Programming Language :: Python :: 3.10
Classifier: Programming Language :: Python :: 3.11
Classifier: Intended Audience :: Developers
Classifier: Topic :: Text Processing
Classifier: License :: OSI Approved :: GNU Affero General Public License v3 or later (AGPLv3+)
Requires-Python: >=3.9
License-File: LICENSE
Requires-Dist: pip>=2.3.1
Requires-Dist: PyMuPDF>=1.25.0
Requires-Dist: pytesseract>=0.3.13
Requires-Dist: xlrd>=2.0.1
Requires-Dist: openpyxl>=3.1.5
Provides-Extra: azure
Requires-Dist: azure-ai-documentintelligence>=1.0.2; extra == "azure"
Requires-Dist: azure-core>=1.24.0; extra == "azure"
Dynamic: license-file
